django_tex/__init__.py
django_tex/core.py
django_tex/engine.py
django_tex/environment.py
django_tex/exceptions.py
django_tex/extensions.py
django_tex/filters.py
django_tex/models.py
django_tex/response.py
django_tex/shortcuts.py
django_tex/views.py
django_tex-1.1.11.dist-info/licenses/AUTHORS
django_tex-1.1.11.dist-info/licenses/LICENSE
django_tex-1.1.11.dist-info/METADATA
django_tex-1.1.11.dist-info/WHEEL
django_tex-1.1.11.dist-info/top_level.txt
django_tex-1.1.11.dist-info/RECORD
