Metadata-Version: 2.4
Name: django-tex
Version: 1.1.11
Summary: A simple Django app to render Latex templates and compile them into PDF files.
Home-page: https://github.com/weinbusch/django-tex
Author: Martin Bierbaum
License: MIT
Keywords: django latex jinja2
Requires-Python: >=3.6.2
License-File: LICENSE
License-File: AUTHORS
Requires-Dist: django>=2.2
Requires-Dist: jinja2>=2.9
Dynamic: author
Dynamic: description
Dynamic: description-content-type
Dynamic: home-page
Dynamic: keywords
Dynamic: license
Dynamic: license-file
Dynamic: requires-dist
Dynamic: requires-python
Dynamic: summary
